antm/__init__.py
antm/aligned_clustering_layer.py
antm/cm.py
antm/contextual_embedding_layer.py
antm/ctfidf.py
antm/data2vec.py
antm/diversity_metrics.py
antm/main.py
antm/sws.py
antm/text_processing.py
antm/topic_representation_layer.py
antm-0.1.7.dist-info/LICENSE
antm-0.1.7.dist-info/METADATA
antm-0.1.7.dist-info/WHEEL
antm-0.1.7.dist-info/top_level.txt
antm-0.1.7.dist-info/RECORD
