Metadata-Version: 2.1
Name: antm
Version: 0.1.7
Summary: Aligned Neural Topic Model for Exploring Evolving Topics
Home-page: https://github.com/hamedR96/ANTM
Author: Hamed Rahimi
Author-email: <hamed.rahimi@sorbonne-universite.fr
Project-URL: Bug Tracker, https://github.com/hamedR96/ANTM/issues
Classifier: Programming Language :: Python :: 3
Classifier: License :: OSI Approved :: MIT License
Classifier: Operating System :: MacOS :: MacOS X 
Classifier: Operating System :: Unix 
Classifier: Operating System :: Microsoft :: Windows 
License-File: LICENSE
Requires-Dist: hdbscan
Requires-Dist: swifter
Requires-Dist: sentence-transformers
Requires-Dist: umap-learn
Requires-Dist: transformers
Requires-Dist: torch
Requires-Dist: gensim
Requires-Dist: plotly
Requires-Dist: matplotlib
Requires-Dist: pyarrow
Requires-Dist: kaleido
